acrcasppi_ml/__init__.py
acrcasppi_ml/prediction.py
acrcasppi_ml/rf_ac_1.pkl
acrcasppi_ml/rf_ct_1.pkl
acrcasppi_ml/rf_ld_1.pkl
acrcasppi_ml-0.0.1.dist-info/LICENSE.txt
acrcasppi_ml-0.0.1.dist-info/METADATA
acrcasppi_ml-0.0.1.dist-info/WHEEL
acrcasppi_ml-0.0.1.dist-info/top_level.txt
acrcasppi_ml-0.0.1.dist-info/RECORD
