Metadata-Version: 2.1
Name: acrcasppi-ml
Version: 0.0.1
Summary: A package for predicting protein-protein interaction between CRISPR-associated protein (Cas) and Anti-CRISPR protein (Acr).
Author-email: Sneha Murmu <murmu.sneha22@gmail.com>, Himanshushekhar Chaurasia <hschaurasia12@gmail.com>, Sunil Archak <sunil.archak@gmail.com>
Project-URL: Homepage, https://github.com/snehaiasri/acrcasppi
Project-URL: Bug Tracker, https://github.com/snehaiasri/acrcasppi/issues
Classifier: Programming Language :: Python :: 3
Classifier: License :: OSI Approved :: GNU General Public License v3 (GPLv3)
Classifier: Operating System :: OS Independent
Requires-Python: >=3.9
License-File: LICENSE.txt
